[
    {
        "fileName" : "25.jpg",
        "title" : "a",
        "desc" : "Hello World"
    },
    {
        "fileName": "26.jpg",
        "title": "a",
        "desc": "Hello World"
    },
    {
        "fileName": "27.jpg",
        "title": "a",
        "desc": "Hello World"
    },
    {
        "fileName": "28.jpg",
        "title": "a",
        "desc": "Hello World"
    },
    {
        "fileName": "29.jpg",
        "title": "a",
        "desc": "Hello World"
    },
    {
        "fileName": "30.jpg",
        "title": "a",
        "desc": "Hello World"
    },
    {
        "fileName": "31.jpg",
        "title": "a",
        "desc": "Hello World"
    },
    {
        "fileName": "32.jpg",
        "title": "a",
        "desc": "Hello World"
    },
    {
        "fileName": "33.jpg",
        "title": "a",
        "desc": "Hello World"
    },
    {
        "fileName": "34.jpg",
        "title": "a",
        "desc": "Hello World"
    },
    {
        "fileName": "35.jpg",
        "title": "a",
        "desc": "Hello World"
    },
    {
        "fileName": "36.jpg",
        "title": "a",
        "desc": "Hello World"
    },
    {
        "fileName": "37.jpg",
        "title": "a",
        "desc": "Hello World"
    },
    {
        "fileName": "38.jpg",
        "title": "a",
        "desc": "Hello World"
    },
    {
        "fileName": "39.jpg",
        "title": "a",
        "desc": "Hello World"
    }
]